{
    "data": [
        {
            "type": "number",
            "order": "random",
            "quantity": "10k",
            "bubble": 3.876751875,
            "heap": 0.028514374999999995,
            "insertion": 1.759440541,
            "merge": 0.018940665999999995
        },
        {
            "type": "number",
            "order": "random",
            "quantity": "50k",
            "bubble": 98.22798145799999,
            "heap": 0.1795817909999995,
            "insertion": 44.740931708,
            "merge": 0.11242491700000024
        },
        {
            "type": "number",
            "order": "random",
            "quantity": "100k",
            "bubble": 394.38566612500006,
            "heap": 0.38935495800001263,
            "insertion": 176.378654791,
            "merge": 0.23895425000000614
        },
        {
            "type": "number",
            "order": "descending",
            "quantity": "10k",
            "bubble": 6.886257792000038,
            "heap": 0.02857391700001699,
            "insertion": 3.942171333000033,
            "merge": 0.01626854199992067
        },
        {
            "type": "number",
            "order": "descending",
            "quantity": "50k",
            "bubble": 133.42529962499998,
            "heap": 0.17160554199995204,
            "insertion": 89.22219058399992,
            "merge": 0.09176204199991389
        },
        {
            "type": "number",
            "order": "descending",
            "quantity": "100k",
            "bubble": 535.7625365420001,
            "heap": 0.36146770799996375,
            "insertion": 354.96300070899997,
            "merge": 0.19271595800000796
        },
        {
            "type": "number",
            "order": "ascending",
            "quantity": "10k",
            "bubble": 0.0004565409999486292,
            "heap": 0.030809583000063867,
            "insertion": 0.0008521669999481674,
            "merge": 0.015432584000109273
        },
        {
            "type": "number",
            "order": "ascending",
            "quantity": "50k",
            "bubble": 0.002349333999973169,
            "heap": 0.18525533399997585,
            "insertion": 0.004289707999987513,
            "merge": 0.08835374999989654
        },
        {
            "type": "number",
            "order": "ascending",
            "quantity": "100k",
            "bubble": 0.004659749999973428,
            "heap": 0.3959647500000756,
            "insertion": 0.008595458000172584,
            "merge": 0.18697416700001668
        }
    ]
}
